safe_result/__init__.py
safe_result/py.typed
safe_result-4.0.3.dist-info/METADATA
safe_result-4.0.3.dist-info/WHEEL
safe_result-4.0.3.dist-info/licenses/LICENSE
safe_result-4.0.3.dist-info/RECORD
