Metadata-Version: 2.4
Name: safe-result
Version: 4.0.3
Summary: A Python library providing a Result type for elegant error handling, inspired by Rust's Result type.
Project-URL: Homepage, https://github.com/overflowy/safe-result
Project-URL: Documentation, https://github.com/overflowy/safe-result#readme
Project-URL: Issues, https://github.com/overflowy/safe-result/issues
Project-URL: Source, https://github.com/overflowy/safe-result
Author-email: overflowy <overflowy@riseup.net>
License: MIT
License-File: LICENSE
Keywords: error-handling,functional,result,rust-inspired,type-safety
Classifier: Development Status :: 5 - Production/Stable
Classifier: Intended Audience :: Developers
Classifier: License :: OSI Approved :: MIT License
Classifier: Programming Language :: Python :: 3
Classifier: Programming Language :: Python :: 3.10
Classifier: Programming Language :: Python :: 3.11
Classifier: Programming Language :: Python :: 3.12
Classifier: Topic :: Software Development :: Libraries :: Python Modules
Classifier: Typing :: Typed
Requires-Python: >=3.10
